<annotation verified="yes">
    <folder>Annotation</folder>
    <filename>images%2520(82).jpg</filename>
    <path>cat_data_set-PascalVOC-export/Annotations/images%2520(82).jpg</path>
    <source>
        <database>Unknown</database>
    </source>
    <size>
        <width>276</width>
        <height>183</height>
        <depth>3</depth>
    </size>
    <segmented>0</segmented>
    <object>
    <name>Cat_Face</name>
    <pose>Unspecified</pose>
    <truncated>0</truncated>
    <difficult>0</difficult>
    <bndbox>
        <xmin>71.35521380345087</xmin>
        <ymin>13.041855203619908</ymin>
        <xmax>231.19917479369843</xmax>
        <ymax>158.77941176470588</ymax>
    </bndbox>
</object>
</annotation>
